aind_metadata_service/__init__.py
aind_metadata_service/client.py
aind_metadata_service/models.py
aind_metadata_service/response_handler.py
aind_metadata_service/server.py
aind_metadata_service/settings.py
aind_metadata_service/labtracks/__init__.py
aind_metadata_service/labtracks/client.py
aind_metadata_service/labtracks/query_builder.py
aind_metadata_service/mgi/__init__.py
aind_metadata_service/mgi/client.py
aind_metadata_service/mgi/mapping.py
aind_metadata_service/sharepoint/__init__.py
aind_metadata_service/sharepoint/client.py
aind_metadata_service/sharepoint/utils.py
aind_metadata_service/sharepoint/las2020/__init__.py
aind_metadata_service/sharepoint/las2020/mapping.py
aind_metadata_service/sharepoint/las2020/models.py
aind_metadata_service/sharepoint/nsb2019/__init__.py
aind_metadata_service/sharepoint/nsb2019/mapping.py
aind_metadata_service/sharepoint/nsb2019/models.py
aind_metadata_service/sharepoint/nsb2023/__init__.py
aind_metadata_service/sharepoint/nsb2023/mapping.py
aind_metadata_service/sharepoint/nsb2023/models.py
aind_metadata_service/slims/__init__.py
aind_metadata_service/slims/client.py
aind_metadata_service/slims/table_handler.py
aind_metadata_service/slims/ecephys/__init__.py
aind_metadata_service/slims/ecephys/handler.py
aind_metadata_service/slims/ecephys/mapping.py
aind_metadata_service/slims/histology/__init__.py
aind_metadata_service/slims/histology/handler.py
aind_metadata_service/slims/histology/mapping.py
aind_metadata_service/slims/imaging/__init__.py
aind_metadata_service/slims/imaging/handler.py
aind_metadata_service/slims/imaging/mapping.py
aind_metadata_service/slims/viral_injection/__init__.py
aind_metadata_service/slims/viral_injection/handler.py
aind_metadata_service/slims/viral_injection/mapping.py
aind_metadata_service/slims/water_restriction/__init__.py
aind_metadata_service/slims/water_restriction/handler.py
aind_metadata_service/slims/water_restriction/mapping.py
aind_metadata_service/smartsheet/__init__.py
aind_metadata_service-0.24.0.dist-info/licenses/LICENSE
aind_metadata_service-0.24.0.dist-info/METADATA
aind_metadata_service-0.24.0.dist-info/WHEEL
aind_metadata_service-0.24.0.dist-info/top_level.txt
aind_metadata_service-0.24.0.dist-info/RECORD
