Metadata-Version: 2.4
Name: aind_metadata_service
Version: 0.24.0
Summary: REST service to retrive metadata from databases.
Author: Allen Institute for Neural Dynamics
License: MIT
Classifier: Programming Language :: Python :: 3
Requires-Python: >=3.10
License-File: LICENSE
Requires-Dist: pydantic-settings>=2.0
Requires-Dist: pydantic>=2.10
Requires-Dist: aind-metadata-mapper[bergamo]==0.21.0
Requires-Dist: aind-data-schema==1.2.0
Requires-Dist: typing-extensions==4.12.2
Provides-Extra: dev
Requires-Dist: aind-metadata-service[server]; extra == "dev"
Requires-Dist: aind-metadata-service[client]; extra == "dev"
Requires-Dist: black; extra == "dev"
Requires-Dist: coverage; extra == "dev"
Requires-Dist: flake8; extra == "dev"
Requires-Dist: interrogate; extra == "dev"
Requires-Dist: isort; extra == "dev"
Requires-Dist: Sphinx; extra == "dev"
Requires-Dist: pre-commit; extra == "dev"
Provides-Extra: server
Requires-Dist: pyodbc==5.1.0; extra == "server"
Requires-Dist: office365-rest-python-client==2.4.1; extra == "server"
Requires-Dist: smartsheet-python-sdk==3.0.2; extra == "server"
Requires-Dist: fastapi==0.115.0; extra == "server"
Requires-Dist: uvicorn[standard]==0.31.0; extra == "server"
Requires-Dist: python-dateutil; extra == "server"
Requires-Dist: aind-slims-api==0.1.21; extra == "server"
Requires-Dist: azure-identity==1.15.0; extra == "server"
Requires-Dist: networkx; extra == "server"
Requires-Dist: boto3; extra == "server"
Provides-Extra: client
Requires-Dist: requests; extra == "client"
Dynamic: license-file
